langport/__init__.py
langport/constants.py
langport/version.py
langport/core/__init__.py
langport/core/base_node.py
langport/core/cluster_node.py
langport/core/cluster_worker.py
langport/core/dispatch.py
langport/model/__init__.py
langport/model/compression.py
langport/model/model_adapter.py
langport/model/model_args.py
langport/model/monkey_patch_non_inplace.py
langport/model/adapters/__init__.py
langport/model/adapters/baichuan.py
langport/model/adapters/baichuan2.py
langport/model/adapters/baize.py
langport/model/adapters/bard.py
langport/model/adapters/billa.py
langport/model/adapters/changgpt.py
langport/model/adapters/chatglm.py
langport/model/adapters/chatgpt.py
langport/model/adapters/claude.py
langport/model/adapters/codegen.py
langport/model/adapters/codellama.py
langport/model/adapters/dolly_v2.py
langport/model/adapters/falcon.py
langport/model/adapters/firefly.py
langport/model/adapters/internlm.py
langport/model/adapters/koala.py
langport/model/adapters/llama.py
langport/model/adapters/longchat.py
langport/model/adapters/mistral.py
langport/model/adapters/ningyu.py
langport/model/adapters/oasst_pythia.py
langport/model/adapters/openbuddy.py
langport/model/adapters/phoenix.py
langport/model/adapters/qwen.py
langport/model/adapters/robin.py
langport/model/adapters/rwkv.py
langport/model/adapters/snoozy.py
langport/model/adapters/stable_lm.py
langport/model/adapters/starcoder.py
langport/model/adapters/t5.py
langport/model/adapters/text2vec.py
langport/model/adapters/tigerbot.py
langport/model/adapters/vicuna.py
langport/model/adapters/wizardlm.py
langport/model/executor/__init__.py
langport/model/executor/base.py
langport/model/executor/ggml.py
langport/model/executor/huggingface.py
langport/model/executor/optimum.py
langport/model/executor/embedding/__init__.py
langport/model/executor/embedding/huggingface.py
langport/model/executor/generation/__init__.py
langport/model/executor/generation/chatgpt.py
langport/model/executor/generation/ggml.py
langport-0.3.11.dist-info/LICENSE
langport-0.3.11.dist-info/METADATA
langport-0.3.11.dist-info/WHEEL
langport-0.3.11.dist-info/top_level.txt
langport-0.3.11.dist-info/RECORD
