Metadata-Version: 2.1
Name: langport
Version: 0.3.11
Summary: A large language model serving platform.
Project-URL: Homepage, https://github.com/vtuber-plan/langport
Project-URL: Bug Tracker, https://github.com/vtuber-plan/langport/issues
Classifier: Programming Language :: Python :: 3
Classifier: License :: OSI Approved :: Apache Software License
Requires-Python: >=3.8
License-File: LICENSE
Requires-Dist: fastapi
Requires-Dist: httpx
Requires-Dist: pydantic <=1.10.13
Requires-Dist: requests
Requires-Dist: rich >=10.0.0
Requires-Dist: datasets >=2.14.5
Requires-Dist: cachetools
Requires-Dist: asyncache
Requires-Dist: shortuuid
Requires-Dist: tokenizers >=0.14.1
Requires-Dist: chatproto
Requires-Dist: transformers >=4.34.0
Requires-Dist: uvicorn
Requires-Dist: wandb
Requires-Dist: tenacity >=8.2.2
Provides-Extra: dev
Requires-Dist: black ==23.3.0 ; extra == 'dev'
Requires-Dist: pylint ==2.8.2 ; extra == 'dev'
Provides-Extra: ggml
Requires-Dist: ctransformers ; extra == 'ggml'
Provides-Extra: optimum
Requires-Dist: onnx ; extra == 'optimum'
Requires-Dist: onnxruntime ; extra == 'optimum'
Requires-Dist: optimum ; extra == 'optimum'
